CHANGELOG.rst
LICENSE.txt
MANIFEST.in
README.rst
requirements.txt
setup.cfg
setup.py
scine_art/__init__.py
scine_art/__main__.py
scine_art/_version.py
scine_art/database.py
scine_art/experimental.py
scine_art/io.py
scine_art/molecules.py
scine_art/reaction_template.py
scine_art.egg-info/PKG-INFO
scine_art.egg-info/SOURCES.txt
scine_art.egg-info/dependency_links.txt
scine_art.egg-info/entry_points.txt
scine_art.egg-info/not-zip-safe
scine_art.egg-info/requires.txt
scine_art.egg-info/top_level.txt
scine_art/test/__init__.py
scine_art/test/test_io.py
scine_art/test/test_molecules.py
scine_art/test/resources/__init__.py